LICENSE.txt
MANIFEST.in
README.md
setup.py
python/jtorch/__init__.py
python/jtorch/autograd.py
python/jtorch/compiler.py
python/jtorch/cuda.py
python/jtorch/distributed.py
python/jtorch/misc.py
python/jtorch/optim.py
python/jtorch.egg-info/PKG-INFO
python/jtorch.egg-info/SOURCES.txt
python/jtorch.egg-info/dependency_links.txt
python/jtorch.egg-info/requires.txt
python/jtorch.egg-info/top_level.txt
python/jtorch/nn/__init__.py
python/jtorch/nn/init.py
python/jtorch/nn/utils/__init__.py
python/jtorch/nn/utils/rnn.py
python/jtorch/src/jtorch_core.cc
python/jtorch/src/jtorch_core.h
python/jtorch/test/test_conflict_func.py
python/jtorch/test/test_function.py
python/jtorch/test/test_misc.py
python/jtorch/test/test_tutorial.py
python/jtorch/tutorial/auto_grad1.py
python/jtorch/tutorial/auto_grad2.py
python/jtorch/tutorial/auto_grad3.py
python/jtorch/tutorial/auto_grad4.py
python/jtorch/tutorial/auto_grad5_optim.py
python/jtorch/tutorial/auto_grad6_module.py
python/jtorch/tutorial/auto_grad7_dynet.py
python/jtorch/tutorial/quickstart.py
python/jtorch/utils/__init__.py
python/jtorch/utils/checkpoint.py
python/jtorch/utils/data.py
python/jtorch/utils/dtype.py
python/jtorch/utils/pip_publish.py
python/jtorch/vision/_internally_replaced_utils.py
python/jtorch/vision/transforms.py
python/jtorch/vision/utils.py
python/jtorch/vision/datasets/__init__.py
python/jtorch/vision/datasets/mnist.py
python/jtorch/vision/datasets/utils.py
python/jtorch/vision/datasets/vision.py
python/torch/__init__.py
python/torch/autograd.py