Metadata-Version: 2.1
Name: jtorch
Version: 0.1.3
Summary: jtorch project
Home-page: https://github.com/JITTorch/jtorch
Author: jtorch
Author-email: jtorch@qq.com
License: UNKNOWN
Project-URL: Bug Tracker, https://github.com/JITTorch/jtorch/issues
Platform: UNKNOWN
Classifier: Programming Language :: Python :: 3
Classifier: Operating System :: OS Independent
Requires-Python: >=3.7
License-File: LICENSE.txt
